{
    "definition": "Describing an optetrode micro drive.",
    "description": {
        "type": "string",
        "value": "Optetrode - combined tetrodes and optic fibre in a micro drive."
    },
    "identifier": "mikkel_drive_optetrode",
    "manufacturer": {
        "definition": "The manufacturer of the drive e.g. ordered from a company.",
        "type": "string",
        "value": "Axona made the chassie and tetrodes and optic fibre is assembled on site"
    },
    "notes": {
        "type": "string",
        "value": ""
    },
    "optic_fibre_count": {
        "definition": "Number of optic fibres in drive.",
        "type": "int",
        "value": 1
    },
    "registration_type": {
        "definition": "The type of registration.",
        "type": "string",
        "value": "extracellular"
    },
    "tetrode_count": {
        "definition": "Number of tetrodes in drive.",
        "type": "int",
        "value": 4
    }
}